functoolsplus.py
kwplus.py
kwrepr.py
kwvars.py
kwplus/__init__.py
kwplus/functools.py
kwplus/repr.py
kwplus/variations.py
kwplus-1.0.1.dist-info/LICENSE
kwplus-1.0.1.dist-info/METADATA
kwplus-1.0.1.dist-info/WHEEL
kwplus-1.0.1.dist-info/top_level.txt
kwplus-1.0.1.dist-info/RECORD
