Metadata-Version: 2.1
Name: kwplus
Version: 1.0.1
Summary: Keyword arguments on steroids
Home-page: https://github.com/wecacuee/kwplus
Author: Vikas Dhiman
Author-email: wecacuee@github.com
License: MIT
Platform: UNKNOWN
Classifier: Development Status :: 3 - Alpha
Classifier: Programming Language :: Python :: 3
Classifier: License :: OSI Approved :: MIT License
Classifier: Operating System :: OS Independent
Requires-Python: >=3.5
